CHANGES
LICENSE
MANIFEST.in
README.rst
setup.py
django_love_utils.egg-info/PKG-INFO
django_love_utils.egg-info/SOURCES.txt
django_love_utils.egg-info/dependency_links.txt
django_love_utils.egg-info/not-zip-safe
django_love_utils.egg-info/requires.txt
django_love_utils.egg-info/top_level.txt
love_utils/__init__.py
love_utils/apps.py
love_utils/admin/__init__.py
love_utils/admin/helpes.py
love_utils/debug/__init__.py
love_utils/debug/pprint.py
love_utils/models/__init__.py
love_utils/models/fields.py
love_utils/static/love_utils/js/orderable.js
love_utils/templatetags/__init__.py
love_utils/templatetags/common.py
love_utils/utils/__init__.py
love_utils/utils/signals.py