Metadata-Version: 1.1
Name: django-love-utils
Version: 0.1.1
Summary: Utils for django project
Home-page: https://github.com/ailove-dev/django-love-utils
Author: Ailove
Author-email: ailove@ailove.com
License: MIT
Platform: any
Classifier: Development Status :: 4 - Beta
Classifier: Development Status :: 5 - Production/Stable
Classifier: Environment :: Web Environment
Classifier: Framework :: Django
Classifier: Programming Language :: Python
Classifier: Programming Language :: Python :: 3
Classifier: Topic :: Utilities
